CHANGES.rst
LICENSE.rst
MANIFEST.in
README.rst
VERSION
setup.cfg
setup.py
bin/aimes-bundle-manager
bin/aimes-bundle-query
bin/aimes-bundle-version
bin/aimes-bundled
src/aimes/__init__.py
src/aimes/__init__.pyc
src/aimes/bundlec
src/aimes.bundle.egg-info/PKG-INFO
src/aimes.bundle.egg-info/SOURCES.txt
src/aimes.bundle.egg-info/dependency_links.txt
src/aimes.bundle.egg-info/namespace_packages.txt
src/aimes.bundle.egg-info/not-zip-safe
src/aimes.bundle.egg-info/requires.txt
src/aimes.bundle.egg-info/top_level.txt
src/aimes/bundle/.bundle_manager.py.swp
src/aimes/bundle/.resource_bundle.py.swp
src/aimes/bundle/.session.py.swp
src/aimes/bundle/VERSION
src/aimes/bundle/VERSION.git
src/aimes/bundle/__init__.py
src/aimes/bundle/__init__.pyc
src/aimes/bundle/bundle_manager.py
src/aimes/bundle/bundle_manager.pyc
src/aimes/bundle/exceptions.py
src/aimes/bundle/exceptions.pyc
src/aimes/bundle/resource_bundle.py
src/aimes/bundle/resource_bundle.pyc
src/aimes/bundle/result.dat
src/aimes/bundle/session.py
src/aimes/bundle/session.pyc
src/aimes/bundle/version.py
src/aimes/bundle/agent/.bundle_agent.py.swp
src/aimes/bundle/agent/.run-iperf-client.sh.swp
src/aimes/bundle/agent/.start-iperf-server-daemon.sh.swp
src/aimes/bundle/agent/__init__.py
src/aimes/bundle/agent/__init__.pyc
src/aimes/bundle/agent/bundle_agent.py
src/aimes/bundle/agent/bundle_agent.pyc
src/aimes/bundle/agent/run-iperf-client.sh
src/aimes/bundle/agent/start-iperf-server-daemon.sh
src/aimes/bundle/configs/.aimes_bundle_resource.json.swp
src/aimes/bundle/configs/aimes_bundle_resource.json
src/aimes/bundle/configs/aimes_bundle_resources.conf
src/aimes/bundle/db/.database.py.swp
src/aimes/bundle/db/__init__.py
src/aimes/bundle/db/__init__.pyc
src/aimes/bundle/db/database.py
src/aimes/bundle/db/database.pyc
src/aimes/bundle/tests/api/test_bundle_manager.py
src/aimes/bundle/third_party/iperf-3.0.11-source.tar.gz