Metadata-Version: 1.1
Name: aimes.bundle
Version: 0.1.1
Summary: Bundle based Information System for AIMES
Home-page: https://github.com/Francis-Liu/aimes.bundle
Author: Francis Liu
Author-email: liux2102@umn.edu
License: MIT
Keywords: aimes bundle
Platform: UNKNOWN
Classifier: Development Status :: 4 - Beta
Classifier: Intended Audience :: Science/Research
Classifier: Environment :: Console
Classifier: License :: OSI Approved :: MIT License
Classifier: Programming Language :: Python
Classifier: Programming Language :: Python :: 2
Classifier: Programming Language :: Python :: 2.6
Classifier: Programming Language :: Python :: 2.7
Classifier: Topic :: Utilities
Classifier: Topic :: System :: Distributed Computing
Classifier: Topic :: Scientific/Engineering
Classifier: Operating System :: MacOS :: MacOS X
Classifier: Operating System :: POSIX
Classifier: Operating System :: Unix
